gemelli/__init__.py
gemelli/_defaults.py
gemelli/base.py
gemelli/citations.bib
gemelli/ctf.py
gemelli/factorization.py
gemelli/matrix_completion.py
gemelli/optspace.py
gemelli/preprocessing.py
gemelli/rpca.py
gemelli/simulations.py
gemelli/tempted.py
gemelli/testing.py
gemelli/utils.py
gemelli/q2/__init__.py
gemelli/q2/_format.py
gemelli/q2/_transformer.py
gemelli/q2/_type.py
gemelli/q2/_visualizer.py
gemelli/q2/plugin_setup.py
gemelli/q2/qc_assests/index.html
gemelli/q2/tests/__init__.py
gemelli/q2/tests/test_data_transformations.py
gemelli/q2/tests/test_format.py
gemelli/q2/tests/test_method.py
gemelli/q2/tests/test_optspace.py
gemelli/q2/tests/test_rpca_method.py
gemelli/q2/tests/test_transformer.py
gemelli/scripts/__init__.py
gemelli/scripts/_standalone_ctf.py
gemelli/scripts/_standalone_rpca.py
gemelli/scripts/_standalone_tempted.py
gemelli/scripts/_standalone_transforms.py
gemelli/scripts/tests/__init__.py
gemelli/scripts/tests/test_standalone_ctf.py
gemelli/scripts/tests/test_standalone_rpca.py
gemelli/scripts/tests/test_standalone_transforms.py
gemelli-0.0.12.dist-info/LICENSE
gemelli-0.0.12.dist-info/METADATA
gemelli-0.0.12.dist-info/WHEEL
gemelli-0.0.12.dist-info/entry_points.txt
gemelli-0.0.12.dist-info/top_level.txt
gemelli-0.0.12.dist-info/RECORD
