Metadata-Version: 2.1
Name: gemelli
Version: 0.0.12
Summary: Robust Aitchison Tensor Decomposition for sparse count data
Author: gemelli development team
Author-email: cmartino@eng.ucsd.edu
Maintainer: gemelli development team
Maintainer-email: cmartino@eng.ucsd.edu
License: BSD-3-Clause
Classifier: Development Status :: 3 - Alpha
Classifier: License :: OSI Approved :: BSD License
Classifier: Topic :: Software Development :: Libraries
Classifier: Topic :: Scientific/Engineering
Classifier: Topic :: Scientific/Engineering :: Bio-Informatics
Classifier: Programming Language :: Python :: 3
Classifier: Programming Language :: Python :: 3 :: Only
Classifier: Operating System :: Unix
Classifier: Operating System :: POSIX
Classifier: Operating System :: MacOS :: MacOS X
License-File: LICENSE
Requires-Dist: numpy>=1.12.1
Requires-Dist: click
Requires-Dist: pandas>=0.10.0
Requires-Dist: scipy>=0.19.1
Requires-Dist: nose>=1.3.7
Requires-Dist: scikit-learn>=0.18.1
Requires-Dist: scikit-bio>0.5.3
Requires-Dist: biom-format
Requires-Dist: h5py
Requires-Dist: iow
Requires-Dist: tax2tree
